LICENSE
MANIFEST.in
README.md
lgpl-3.0.txt
setup.cfg
setup.py
versioneer.py
python/kabaret/__init__.py
python/kabaret.flow_button_pages.egg-info/PKG-INFO
python/kabaret.flow_button_pages.egg-info/SOURCES.txt
python/kabaret.flow_button_pages.egg-info/dependency_links.txt
python/kabaret.flow_button_pages.egg-info/requires.txt
python/kabaret.flow_button_pages.egg-info/top_level.txt
python/kabaret/flow_button_pages/__init__.py
python/kabaret/flow_button_pages/_version.py
python/kabaret/flow_button_pages/button_home.py
python/kabaret/flow_button_pages/icons/__init__.py
python/kabaret/flow_button_pages/icons/clap-blue.png
python/kabaret/flow_button_pages/icons/clap-green.png
python/kabaret/flow_button_pages/icons/clap-orange.png
python/kabaret/flow_button_pages/icons/clap-pink.png
python/kabaret/flow_button_pages/icons/clap-red.png
python/kabaret/flow_button_pages/icons/reel-blue.png
python/kabaret/flow_button_pages/icons/reel-green.png
python/kabaret/flow_button_pages/icons/reel-orange.png
python/kabaret/flow_button_pages/icons/reel-pink.png
python/kabaret/flow_button_pages/icons/reel-red.png
python/kabaret/flow_button_pages/icons/screen-blue.png
python/kabaret/flow_button_pages/icons/screen-green.png
python/kabaret/flow_button_pages/icons/screen-orange.png
python/kabaret/flow_button_pages/icons/screen-pink.png
python/kabaret/flow_button_pages/icons/screen-red.png
python/kabaret/flow_button_pages/ui/__init__.py
python/kabaret/flow_button_pages/ui/button_map.py
python/kabaret/flow_button_pages/ui/html_button.py