Metadata-Version: 2.1
Name: kabaret.flow-button-pages
Version: 0.1.12
Summary: A button based collection of custom_page widgets to use in your flow
Home-page: https://gitlab.com/kabaretstudio/kabaret.flow_button_pages
Author: Damien "dee" Coureau
Author-email: kabaret-dev@googlegroups.com
License: LGPLv3+
Keywords: kabaret gui vfx animation pipeline dataflow workflow asset manager
Platform: UNKNOWN
Classifier: Development Status :: 4 - Beta
Classifier: Intended Audience :: Developers
Classifier: Operating System :: OS Independent
Classifier: Programming Language :: Python :: 2.7
Classifier: Programming Language :: Python :: 3.3
Classifier: License :: OSI Approved :: GNU Lesser General Public License v3 or later (LGPLv3+)
Requires-Python: >=2.7,!=3.0.*,!=3.1.*,!=3.2.*
